covid19certificate/__init__.py
covid19certificate/ui_main.py
covid19certificate/ui_peopleEdit.py
covid19_certificate_pos-1.2.dist-info/LICENSE.txt
covid19_certificate_pos-1.2.dist-info/METADATA
covid19_certificate_pos-1.2.dist-info/WHEEL
covid19_certificate_pos-1.2.dist-info/entry_points.txt
covid19_certificate_pos-1.2.dist-info/top_level.txt
covid19_certificate_pos-1.2.dist-info/RECORD
