Metadata-Version: 2.1
Name: covid19-certificate-pos
Version: 1.2
Summary: UNKNOWN
Home-page: UNKNOWN
Author: Emmanuel C
Author-email: manuco@users.noreply.github.com
License: GPL v3
Download-URL: https://github.com/manuco/covid19_certificate_pos/archive/1.2.tar.gz
Platform: UNKNOWN
Requires-Dist: python-escpos (<3.1,>=3.0a)
Requires-Dist: PyQt5 (<5.15)
